{"Item1":[{"Description":"Цель","Parameters":[[],[],[],[],[]]},{"Description":"Узел 1","Parameters":[[{"Name":"Продажы","Value":9.5,"ParameterType":0}],[{"Name":"П. 1","Value":13.0,"ParameterType":1}],[{"Name":"П. 1","Value":0.5,"ParameterType":2}],[{"Name":"П. 1","Value":312.0,"ParameterType":3}],[{"Name":"П.1","Value":100.0,"ParameterType":4}]]},{"Description":"Узел 1.1","Parameters":[[{"Name":"Продажы","Value":9.5,"ParameterType":0}],[],[],[{"Name":"П. 1","Value":312.0,"ParameterType":3}],[]]},{"Description":"Узел 2","Parameters":[[],[],[],[],[]]},{"Description":"Узел 2.1","Parameters":[[{"Name":"Продажы","Value":9.5,"ParameterType":0}],[],[],[],[]]},{"Description":"Узел 2.2","Parameters":[[],[],[],[{"Name":"П. 1","Value":312.0,"ParameterType":3}],[]]},{"Description":"Узел 2.2.1","Parameters":[[{"Name":"Перем. изд.","Value":1.0,"ParameterType":0},{"Name":"Пост. изд.","Value":2.0,"ParameterType":0},{"Name":"Налоги","Value":5.5,"ParameterType":0},{"Name":"Продажы","Value":9.5,"ParameterType":0}],[{"Name":"П. 2","Value":5.0,"ParameterType":1},{"Name":"П. 1","Value":13.0,"ParameterType":1}],[{"Name":"П. 1","Value":0.5,"ParameterType":2}],[{"Name":"П. 1","Value":312.0,"ParameterType":3}],[{"Name":"П.1","Value":100.0,"ParameterType":4}]]}],"Item2":[{"From":0,"To":1},{"From":1,"To":2},{"From":0,"To":3},{"From":3,"To":4},{"From":3,"To":5},{"From":5,"To":6}]}